Metadata-Version: 2.1
Name: nnb-binomial
Version: 0.2
Summary: Gaussian distributions
Home-page: UNKNOWN
License: UNKNOWN
Platform: UNKNOWN
